README.md
setup.py
uclgeog_msc/Chapter3_6.py
uclgeog_msc/Chapter3_6A_prerequisites.py
uclgeog_msc/__init__.py
uclgeog_msc/api.py
uclgeog_msc/create_blank_file.py
uclgeog_msc/cylog.py
uclgeog_msc/demofilt1.py
uclgeog_msc/demofilt2.py
uclgeog_msc/demofilt3.py
uclgeog_msc/demofilt4.py
uclgeog_msc/demofilt5.py
uclgeog_msc/discharge.py
uclgeog_msc/download_lai.py
uclgeog_msc/download_snow.py
uclgeog_msc/fire_practical_model.py
uclgeog_msc/fire_practical_satellite.py
uclgeog_msc/fire_practical_telecon.py
uclgeog_msc/geog_data.py
uclgeog_msc/getNOAA.py
uclgeog_msc/get_landcover.py
uclgeog_msc/get_modis_files.py
uclgeog_msc/get_url.py
uclgeog_msc/match_netcdf_to_data.py
uclgeog_msc/modis_tiles.py
uclgeog_msc/move.py
uclgeog_msc/nasa_requests.py
uclgeog_msc/nsat.py
uclgeog_msc/plot_landcover.py
uclgeog_msc/process_timeseries.py
uclgeog_msc/raster_mask.py
uclgeog_msc/save_data.py
uclgeog_msc/today.py
uclgeog_msc/visfig.py
uclgeog_msc.egg-info/PKG-INFO
uclgeog_msc.egg-info/SOURCES.txt
uclgeog_msc.egg-info/dependency_links.txt
uclgeog_msc.egg-info/entry_points.txt
uclgeog_msc.egg-info/top_level.txt