Metadata-Version: 1.1
Name: uclgeog-msc
Version: 1.0.10
Summary: Scientific Computing
Home-page: https://github.com/profLewis/uclgeog_msc_core
Author: Prof. P. Lewis
Author-email: p.lewis@ucl.ac.uk
License: MIT
Keywords: scientific computing
Platform: UNKNOWN
Classifier: Development Status :: 3 - Alpha
Classifier: Intended Audience :: Developers
Classifier: Topic :: Software Development :: Build Tools
Classifier: License :: OSI Approved :: MIT License
Classifier: Programming Language :: Python :: 3.7
